strace_parser/__init__.py
strace_parser/__main__.py
strace_parser/cli.py
strace_parser/json_transformer.py
strace_parser/parser.py
strace_parser/data/__init__.py
strace_parser/data/grammar.txt
strace_parser-0.2.0.dist-info/entry_points.txt
strace_parser-0.2.0.dist-info/LICENSE.txt
strace_parser-0.2.0.dist-info/WHEEL
strace_parser-0.2.0.dist-info/METADATA
strace_parser-0.2.0.dist-info/RECORD
